samlab/__init__.py
samlab/cli/__init__.py
samlab/cli/main.py
samlab/deepvis/__init__.py
samlab/deepvis/templates/base.html
samlab/deepvis/templates/bootstrap-5.3.3-dist.zip
samlab/deepvis/templates/channel.html
samlab/deepvis/templates/dataset.html
samlab/deepvis/templates/index.html
samlab/deepvis/templates/layer.html
samlab/deepvis/templates/sample.html
samlab/deepvis/templates/css/bootstrap-grid.css
samlab/deepvis/templates/css/bootstrap-grid.css.map
samlab/deepvis/templates/css/bootstrap-grid.min.css
samlab/deepvis/templates/css/bootstrap-grid.min.css.map
samlab/deepvis/templates/css/bootstrap-grid.rtl.css
samlab/deepvis/templates/css/bootstrap-grid.rtl.css.map
samlab/deepvis/templates/css/bootstrap-grid.rtl.min.css
samlab/deepvis/templates/css/bootstrap-grid.rtl.min.css.map
samlab/deepvis/templates/css/bootstrap-reboot.css
samlab/deepvis/templates/css/bootstrap-reboot.css.map
samlab/deepvis/templates/css/bootstrap-reboot.min.css
samlab/deepvis/templates/css/bootstrap-reboot.min.css.map
samlab/deepvis/templates/css/bootstrap-reboot.rtl.css
samlab/deepvis/templates/css/bootstrap-reboot.rtl.css.map
samlab/deepvis/templates/css/bootstrap-reboot.rtl.min.css
samlab/deepvis/templates/css/bootstrap-reboot.rtl.min.css.map
samlab/deepvis/templates/css/bootstrap-utilities.css
samlab/deepvis/templates/css/bootstrap-utilities.css.map
samlab/deepvis/templates/css/bootstrap-utilities.min.css
samlab/deepvis/templates/css/bootstrap-utilities.min.css.map
samlab/deepvis/templates/css/bootstrap-utilities.rtl.css
samlab/deepvis/templates/css/bootstrap-utilities.rtl.css.map
samlab/deepvis/templates/css/bootstrap-utilities.rtl.min.css
samlab/deepvis/templates/css/bootstrap-utilities.rtl.min.css.map
samlab/deepvis/templates/css/bootstrap.css
samlab/deepvis/templates/css/bootstrap.css.map
samlab/deepvis/templates/css/bootstrap.min.css
samlab/deepvis/templates/css/bootstrap.min.css.map
samlab/deepvis/templates/css/bootstrap.rtl.css
samlab/deepvis/templates/css/bootstrap.rtl.css.map
samlab-0.4.0.dist-info/entry_points.txt
samlab-0.4.0.dist-info/LICENSE
samlab-0.4.0.dist-info/WHEEL
samlab-0.4.0.dist-info/METADATA
samlab-0.4.0.dist-info/RECORD
